sudden_appearance_calc
