Metadata-Version: 1.0
Name: sudden-appearance-calc
Version: 1.0.1
Summary: Calc
Home-page: UNKNOWN
Author: UNKNOWN
Author-email: kuz.damir.01@gmail.com
License: UNKNOWN
Platform: UNKNOWN
